tree_sitter_epics_cmd/__init__.py
tree_sitter_epics_cmd/__init__.pyi
tree_sitter_epics_cmd/_binding.abi3.so
tree_sitter_epics_cmd/binding.c
tree_sitter_epics_cmd/py.typed
tree_sitter_epics_cmd/queries/highlights.scm
tree_sitter_epics_cmd/queries/injections.scm
tree_sitter_epics_cmd-0.1.5.dist-info/METADATA
tree_sitter_epics_cmd-0.1.5.dist-info/WHEEL
tree_sitter_epics_cmd-0.1.5.dist-info/top_level.txt
tree_sitter_epics_cmd-0.1.5.dist-info/RECORD
tree_sitter_epics_cmd-0.1.5.dist-info/licenses/LICENSE
